openbb_fred/__init__.py
openbb_fred/models/ameribor.py
openbb_fred/models/balance_of_payments.py
openbb_fred/models/bond_indices.py
openbb_fred/models/commercial_paper.py
openbb_fred/models/commodity_spot_prices.py
openbb_fred/models/consumer_price_index.py
openbb_fred/models/dwpcr_rates.py
openbb_fred/models/ecb_interest_rates.py
openbb_fred/models/euro_short_term_rate.py
openbb_fred/models/fed_projections.py
openbb_fred/models/federal_funds_rate.py
openbb_fred/models/ffrmc.py
openbb_fred/models/high_quality_market.py
openbb_fred/models/ice_bofa.py
openbb_fred/models/iorb_rates.py
openbb_fred/models/manufacturing_outlook_ny.py
openbb_fred/models/manufacturing_outlook_texas.py
openbb_fred/models/moody.py
openbb_fred/models/mortgage_indices.py
openbb_fred/models/non_farm_payrolls.py
openbb_fred/models/overnight_bank_funding_rate.py
openbb_fred/models/personal_consumption_expenditures.py
openbb_fred/models/py.typed
openbb_fred/models/regional.py
openbb_fred/models/release_table.py
openbb_fred/models/retail_prices.py
openbb_fred/models/search.py
openbb_fred/models/senior_loan_officer_survey.py
openbb_fred/models/series.py
openbb_fred/models/sofr.py
openbb_fred/models/sonia_rates.py
openbb_fred/models/spot.py
openbb_fred/models/survey_of_economic_conditions_chicago.py
openbb_fred/models/tbffr.py
openbb_fred/models/tips_yields.py
openbb_fred/models/tmc.py
openbb_fred/models/university_of_michigan.py
openbb_fred/models/yield_curve.py
openbb_fred/utils/__init__.py
openbb_fred/utils/average_prices_city_average.json
openbb_fred/utils/average_prices_midwest_urban.json
openbb_fred/utils/average_prices_northeast_urban.json
openbb_fred/utils/average_prices_south_urban.json
openbb_fred/utils/average_prices_west_urban.json
openbb_fred/utils/corporate_spot_rates.csv
openbb_fred/utils/cpi.csv
openbb_fred/utils/fred_base.py
openbb_fred/utils/fred_helpers.py
openbb_fred/utils/harmonized_cpi.csv
openbb_fred/utils/ice_bofa_indices.csv
openbb_fred-1.4.4.dist-info/METADATA
openbb_fred-1.4.4.dist-info/WHEEL
openbb_fred-1.4.4.dist-info/entry_points.txt
openbb_fred-1.4.4.dist-info/RECORD
